{"cameraMode":{"drawMode":0,"name":"Shaded","section":"Shading Mode"},"sceneLighting":true,"audioPlay":false,"sceneViewState":{"showFog":true,"showMaterialUpdate":false,"showSkybox":true,"showFlares":true,"showImageEffects":true,"showParticleSystems":true},"in2DMode":false,"pivot":{"x":1.8807767629623414,"y":0.9095836877822876,"z":7.141747951507568},"rotation":{"x":0.32428887486457827,"y":0.1187630370259285,"z":-0.04107790067791939,"w":0.9375749230384827},"size":3.5028510093688967,"orthographic":false}